datarobotx/idp/__init__.py
datarobotx/idp/autopilot.py
datarobotx/idp/batch_predictions.py
datarobotx/idp/calendars.py
datarobotx/idp/credentials.py
datarobotx/idp/custom_application_source.py
datarobotx/idp/custom_application_source_version.py
datarobotx/idp/custom_applications.py
datarobotx/idp/custom_jobs.py
datarobotx/idp/custom_metrics.py
datarobotx/idp/custom_model_llm_validation.py
datarobotx/idp/custom_model_versions.py
datarobotx/idp/custom_models.py
datarobotx/idp/datasets.py
datarobotx/idp/datasource.py
datarobotx/idp/datastore.py
datarobotx/idp/deployments.py
datarobotx/idp/execution_environment_versions.py
datarobotx/idp/execution_environments.py
datarobotx/idp/guard_configurations.py
datarobotx/idp/llm_blueprints.py
datarobotx/idp/playgrounds.py
datarobotx/idp/projects.py
datarobotx/idp/registered_model_versions.py
datarobotx/idp/retraining_policies.py
datarobotx/idp/use_cases.py
datarobotx/idp/vector_databases.py
datarobotx/idp/common/__init__.py
datarobotx/idp/common/analytics_hooks.py
datarobotx/idp/common/archive_dataset.py
datarobotx/idp/common/asset_resolver.py
datarobotx/idp/common/checkpoint_hooks.py
datarobotx/idp/common/credentials_hooks.py
datarobotx/idp/common/handle_io.py
datarobotx/idp/common/hashing.py
datarobotx/idp/common/path_dataset.py
datarobotx/idp/common/py.typed
datarobotx_idp-0.2.19.dist-info/licenses/LICENSE
datarobotx_idp-0.2.19.dist-info/METADATA
datarobotx_idp-0.2.19.dist-info/WHEEL
datarobotx_idp-0.2.19.dist-info/top_level.txt
datarobotx_idp-0.2.19.dist-info/RECORD
