Metadata-Version: 2.4
Name: datarobotx-idp
Version: 0.2.19
Summary: Suite of utilities for idempotent creation of DataRobot assets
Author-email: DataRobot <support@datarobot.com>
Maintainer-email: DataRobot <support@datarobot.com>
License: DATAROBOT TOOL AND UTILITY AGREEMENT
Project-URL: Homepage, https://github.com/datarobot-community/datarobotx-idp
Keywords: datarobot,idempotent,utilities
Classifier: Programming Language :: Python
Classifier: Programming Language :: Python :: 3
Requires-Python: >=3.10
License-File: LICENSE
Requires-Dist: datarobot<4,>=3.4.0
Requires-Dist: requests<3,>=2.31.0
Provides-Extra: dev
Requires-Dist: ruff==0.1.6; extra == "dev"
Requires-Dist: mypy==1.8.0; extra == "dev"
Requires-Dist: pytest==7.4.3; extra == "dev"
Requires-Dist: types-pyyaml==6.0.12.20240311; extra == "dev"
Requires-Dist: types-requests==2.31.0; extra == "dev"
Requires-Dist: pandas-stubs<=2.1.5; extra == "dev"
Requires-Dist: kedro==0.19.15; extra == "dev"
Requires-Dist: kedro-datasets==3.0.0; extra == "dev"
Requires-Dist: bumpver==2023.1129; extra == "dev"
Dynamic: license-file
